{
  "sections": {
    "image_banner": {
      "type": "image-banner",
      "blocks": {
        "heading": {
          "type": "heading",
          "settings": {
            "heading": "Browse our latest products",
            "heading_size": "h0"
          }
        },
        "button": {
          "type": "buttons",
          "settings": {
            "button_label_1": "Shop all",
            "button_link_1": "shopify:\/\/collections\/all",
            "button_style_secondary_1": true,
            "button_label_2": "",
            "button_link_2": "",
            "button_style_secondary_2": false
          }
        }
      },
      "block_order": [
        "heading",
        "button"
      ],
      "settings": {
        "image_overlay_opacity": 40,
        "image_height": "large",
        "desktop_content_position": "bottom-center",
        "show_text_box": false,
        "desktop_content_alignment": "center",
        "color_scheme": "scheme-3",
        "image_behavior": "none",
        "mobile_content_alignment": "center",
        "stack_images_on_mobile": false,
        "show_text_below": false
      }
    },
    "lookbook_C4Dhrj": {
      "type": "lookbook",
      "blocks": {
        "product_BFBRhF": {
          "type": "Product",
          "settings": {
            "product": "adidas-classic-backpack",
            "product_attribute": "Black"
          }
        },
        "product_QYhHxx": {
          "type": "Product",
          "settings": {
            "product": "adidas-superstar-80s",
            "product_attribute": "White"
          }
        },
        "product_jAxVAh": {
          "type": "Product",
          "settings": {
            "product": "asics-tiger-gel-lyte-v-30-years-of-gel-pack",
            "product_attribute": "Black"
          }
        },
        "product_BqqEpQ": {
          "type": "Product",
          "settings": {
            "product": "adidas-classic-backpack-legend-ink-multicolour",
            "product_attribute": ""
          }
        }
      },
      "block_order": [
        "product_BFBRhF",
        "product_QYhHxx",
        "product_jAxVAh",
        "product_BqqEpQ"
      ],
      "settings": {
        "padding_top": 16,
        "padding_bottom": 16,
        "description": "<p>Our latest collection demonstrates an elegant eccentricity – bold patterns inspired by traditional nomadic dressing, embroidered buttons, ceramic detailing and artisanal stitching contrast with stark, clean-lined silhouettes that showcase refined modernity.<\/p>",
        "description_color": "#000000",
        "background_color": "#000000",
        "image": "shopify:\/\/shop_images\/lookbook_pf22_02.png"
      }
    }
  },
  "order": [
    "image_banner",
    "lookbook_C4Dhrj"
  ]
}
